native/datalog/_init_robotpy_native_datalog.py
native/datalog/robotpy-native-datalog.pc
native/datalog/include/wpi/datalog/DataLog.h
native/datalog/include/wpi/datalog/DataLogBackgroundWriter.h
native/datalog/include/wpi/datalog/DataLogReader.h
native/datalog/include/wpi/datalog/DataLogReaderThread.h
native/datalog/include/wpi/datalog/DataLogWriter.h
native/datalog/include/wpi/datalog/DataLog_c.h
native/datalog/include/wpi/datalog/FileLogger.h
native/datalog/lib/libdatalog.dylib
robotpy_native_datalog-2027.0.0a2.dist-info/METADATA
robotpy_native_datalog-2027.0.0a2.dist-info/WHEEL
robotpy_native_datalog-2027.0.0a2.dist-info/entry_points.txt
robotpy_native_datalog-2027.0.0a2.dist-info/RECORD
