Metadata-Version: 2.4
Name: robotpy-native-datalog
Version: 2027.0.0a2
Summary: WPILib Utility Library
License-Expression: BSD-3-Clause
Requires-Dist: robotpy-native-wpiutil==2027.0.0a2
